firestudio/__init__.py
firestudio/gas_movie_maker.py
firestudio/star_movie_maker.py
firestudio/extensions/firefly.py
firestudio/interpolate/interpolate.py
firestudio/interpolate/scene_interpolate.py
firestudio/interpolate/snapshot_times.txt
firestudio/interpolate/time_helper.py
firestudio/interpolate/time_interpolate.py
firestudio/ntbks/GasStudio_collisionless_example.ipynb
firestudio/ntbks/GasStudio_example.ipynb
firestudio/ntbks/HeaderImage.ipynb
firestudio/ntbks/StarStudio_example.ipynb
firestudio/scripts/cosmo_movie.py
firestudio/scripts/star_testit.sh
firestudio/scripts/testit.sh
firestudio/studios/FIRE_studio.py
firestudio/studios/__init__.py
firestudio/studios/composition.py
firestudio/studios/gas_studio.py
firestudio/studios/simple_studio.py
firestudio/studios/star_studio.py
firestudio/studios/studio.py
firestudio/utils/__init__.py
firestudio/utils/camera_utils.py
firestudio/utils/C_routines/HsmlAndProject_cubicSpline/Makefile
firestudio/utils/C_routines/HsmlAndProject_cubicSpline/main.c
firestudio/utils/C_routines/RayTrace_RGB/Makefile
firestudio/utils/C_routines/RayTrace_RGB/main.c
firestudio/utils/C_routines/RayTrace_RGB/tmp/a.out
firestudio/utils/C_routines/RayTrace_RGB/tmp/main.c
firestudio/utils/C_routines/StellarHsml/forcetree.h
firestudio/utils/C_routines/StellarHsml/main.c
firestudio/utils/C_routines/StellarHsml/makefile
firestudio/utils/C_routines/StellarHsml/makefile2
firestudio/utils/C_routines/StellarHsml/makefile_new
firestudio/utils/C_routines/StellarHsml/makefile_old
firestudio/utils/C_routines/StellarHsml/ngbtree.h
firestudio/utils/C_routines/StellarHsml/ngbtree3d.c
firestudio/utils/C_routines/StellarHsml/ngbtree3d.h
firestudio/utils/C_routines/StellarHsml/nrutil.c
firestudio/utils/C_routines/StellarHsml/nrutil.h
firestudio/utils/C_routines/StellarHsml/proto.h
firestudio/utils/C_routines/StellarHsml/selectb.c
firestudio/utils/C_routines/triband_alphablend/Makefile
firestudio/utils/C_routines/triband_alphablend/main.c
firestudio-2.1.0.dist-info/LICENSE
firestudio-2.1.0.dist-info/METADATA
firestudio-2.1.0.dist-info/WHEEL
firestudio-2.1.0.dist-info/top_level.txt
firestudio-2.1.0.dist-info/RECORD
