Metadata-Version: 2.1
Name: firestudio
Version: 2.1.0
Summary: Rendering code for FIRE simulation data.
Home-page: https://github.com/agurvich/FIRE_studio
Author: Alex Gurvich
Author-email: agurvich@u.northwestern.edu
License: UNKNOWN
Project-URL: Bug Tracker, https://github.com/agurvich/FIRE_studio/issues
Platform: UNKNOWN
Classifier: Programming Language :: Python :: 3
Classifier: License :: OSI Approved :: MIT License
Classifier: Operating System :: OS Independent
Requires-Python: >=3.6
License-File: LICENSE
Requires-Dist: abg-python (>=1.1.1)
Requires-Dist: numpy
Requires-Dist: scipy
Requires-Dist: matplotlib
